capsule/__init__.py
capsule/cli.py
capsule/abstractions/ACmd.py
capsule/abstractions/__init__.py
capsule/cmds/__init__.py
capsule/cmds/deploy.py
capsule/lib/__init__.py
capsule/lib/config_handler.py
capsule/lib/credential_handler.py
capsule/lib/deployer.py
capsule/lib/logging_handler.py
capsule/parser/__init__.py
capsule/parser/parser.py
capsule_terra-0.0.2.dist-info/METADATA
capsule_terra-0.0.2.dist-info/WHEEL
capsule_terra-0.0.2.dist-info/entry_points.txt
capsule_terra-0.0.2.dist-info/top_level.txt
capsule_terra-0.0.2.dist-info/RECORD
