Metadata-Version: 2.1
Name: capsule-terra
Version: 0.0.2
Summary: Capsule is small Python SDK tool you can use to deploy Terra CosmWasm contracts to a given Terra (Cosmos SDK Based) chain.
Home-page: UNKNOWN
Author: 0xFable
Author-email: 0xfable@protonmail.com
License: MIT
Keywords: cosmwasm terra
Platform: UNKNOWN
Requires-Dist: argparse
Requires-Dist: requests
Requires-Dist: terra-sdk
Requires-Dist: toml
